{
  "tmdb_id": 10098,
  "title_sv": "Chaplins pojke",
  "title_original": "The Kid",
  "overview_sv": "En kvinna lämnar sin nyfödde son i en rikemansbil i hopp om att barnet ska få en bra uppväxt. Bilen blir dock stulen av två skurkar som lämnar av barnet i en fattigmansgränd. Det är här den lille luffaren hittar barnet. Fem år senare lever de som far och son tillsammans i både glädje och sorg.",
  "genres": [
    "Komedi",
    "Drama"
  ],
  "release_date": "1921-01-21",
  "runtime": 108,
  "poster_path": "/chLYPp4rxUqXEztTZjYe4aAKG7q.jpg",
  "vote_average": 8.142,
  "age_rating": "Btl",
  "release_date_se": "1922-03-20"
}