{
  "tmdb_id": 10681,
  "title_sv": "WALL-E",
  "title_original": "WALL·E",
  "overview_sv": "Efter hundratals ensamma år av att städa upp vår planet efter människans masskonsumtion och totala eko-förstörelse, upptäcker den nyfikna WALL-E ett helt nytt syfte. När han möter den avancerade sökroboten EVA tar ett storslaget äventyr sin början – ett äventyr som sträcker sig långt bortom jordens soptippar.",
  "genres": [
    "Animerat",
    "Familj",
    "Science Fiction"
  ],
  "release_date": "2008-06-22",
  "release_date_se": "2008-09-05",
  "runtime": 98,
  "poster_path": "/hbhFnRzzg6ZDmm8YAmxBnQpQIPh.jpg",
  "vote_average": 8.11,
  "age_rating": "Btl"
}