{
  "tmdb_id": 1314481,
  "title_sv": "Djävulen bär Prada 2",
  "title_original": "The Devil Wears Prada 2",
  "overview_sv": "När Miranda Priestly närmar sig pensionen tvingas hon konfrontera sitt förflutna. Hon återförenas med Andy Sachs för att möta sin tidigare assistent, nu en mäktig rival – Emily Charlton.",
  "genres": [
    "Drama",
    "Komedi"
  ],
  "release_date": "2026-04-29",
  "release_date_se": "2026-05-01",
  "runtime": 119,
  "poster_path": "/ilqjunDHqUWIwIKJr8peQ9VOSYT.jpg",
  "vote_average": 8.8,
  "age_rating": "Btl"
}