{
  "tmdb_id": 1368337,
  "title_sv": "Odysséen",
  "title_original": "The Odyssey",
  "overview_sv": "I en adaption av Homeros episka epos får vi följa Odysseus, den legendariske kungen av Ithaka, på hans långa och farofyllda resa hem efter det trojanska kriget. Under sin färd ställs han inför gudars nycker, mytologiska monstrum och prövningar som tänjer både hans list och hans mänsklighet till bristningsgränsen.",
  "genres": [
    "Äventyr",
    "Drama",
    "Fantasy"
  ],
  "release_date": "2026-07-15",
  "release_date_se": "2026-07-17",
  "runtime": 0,
  "poster_path": "/hMR0O8eALhrUVmJaNTpOVBO3spo.jpg",
  "vote_average": 0.0,
  "age_rating": ""
}