{
  "tmdb_id": 4816,
  "title_sv": "Ghost Dog - Samurajens väg",
  "title_original": "Ghost Dog: The Way of the Samurai",
  "overview_sv": "Varje samuraj har en herre som han är totalt lojal emot. I Ghost Dogs fall är det Louie, en underhuggare i den italienska maffian som en gång räddat livet på honom. Sedan dess har Ghost Dog utfört ett antal framgångsrika torpedjobb åt Louie. De ses dock aldrig utan håller kontakt genom brevduvor. Ingen vet något om Ghost Dog eller hur han utför sina uppdrag. Han har fått sitt namn efter sin förmåga att komma och gå utan att lämna några spår. När något går fel i ett jobb får han sin herre efter sig och hans enda utväg är att döda hela maffiafamiljen.",
  "genres": [
    "Kriminal",
    "Drama"
  ],
  "release_date": "1999-10-06",
  "runtime": 117,
  "poster_path": "/gkH4zOxIfbb4BEbk9Q4cVOEpDaY.jpg",
  "vote_average": 7.343,
  "age_rating": "",
  "release_date_se": ""
}