{
  "tmdb_id": 543580,
  "title_sv": "They Shall Not Grow Old",
  "title_original": "They Shall Not Grow Old",
  "overview_sv": "Peter Jackson väljer bort den storslagna historiska berättelsen och fokuserar istället på de unga män som drog ut i krig, för att i många fall aldrig återvända. Med ett rikt material av arkivbilder och ljudupptagningar från BBC och Imperial War Museum, återskapar han med full skärpa och klara färger den enorma tragedi som drabbade miljontals människor. Från rekryternas tidiga entusiasm till helvetet i skyttegravarna och all den död och förstörelse de tvingades bevittna på vägen mot den slutliga desillusionen.",
  "genres": [
    "Dokumentär",
    "Historisk",
    "Krig"
  ],
  "release_date": "2018-11-09",
  "runtime": 99,
  "poster_path": "/yMGfJeTXUdIjOqjS0jJfjgYEuYC.jpg",
  "vote_average": 7.767,
  "age_rating": "15",
  "release_date_se": "2019-03-08"
}